agent_as_code/__init__.py
agent_as_code/cli.py
agent_as_code/bin/agent-darwin-amd64
agent_as_code/bin/agent-darwin-arm64
agent_as_code/bin/agent-linux-amd64
agent_as_code/bin/agent-linux-arm64
agent_as_code/bin/agent-windows-amd64.exe
agent_as_code/bin/agent-windows-arm64.exe
agent_as_code-1.1.0.dist-info/METADATA
agent_as_code-1.1.0.dist-info/WHEEL
agent_as_code-1.1.0.dist-info/entry_points.txt
agent_as_code-1.1.0.dist-info/top_level.txt
agent_as_code-1.1.0.dist-info/RECORD
