Metadata-Version: 2.4
Name: agent-as-code
Version: 1.1.0
Summary: Docker-like CLI for AI agents with Enhanced LLM Intelligence
Home-page: https://agent-as-code.myagentregistry.com
Author: Partha Sarathi Kundu
Author-email: Partha Sarathi Kundu <inboxpartha@outlook.com>
License-Expression: MIT
Project-URL: Homepage, https://agent-as-code.myagentregistry.com
Project-URL: Documentation, https://agent-as-code.myagentregistry.com/documentation
Project-URL: github, https://github.com/pxkundu/agent-as-code
Keywords: ai,agents,cli,docker,containers,llm,machine-learning,artificial-intelligence,automation,microservices,devops,ollama,local-llm,model-optimization,agent-generation,intelligent-agents,workflow-automation,sentiment-analysis,chatbot,code-assistant,benchmarking,model-analysis
Platform: any
Classifier: Development Status :: 4 - Beta
Classifier: Intended Audience :: Developers
Classifier: Operating System :: OS Independent
Classifier: Programming Language :: Python :: 3
Classifier: Programming Language :: Python :: 3.8
Classifier: Programming Language :: Python :: 3.9
Classifier: Programming Language :: Python :: 3.10
Classifier: Programming Language :: Python :: 3.11
Classifier: Programming Language :: Python :: 3.12
Classifier: Topic :: Software Development :: Libraries :: Python Modules
Classifier: Topic :: Scientific/Engineering :: Artificial Intelligence
Classifier: Topic :: System :: Software Distribution
Classifier: Topic :: Utilities
Requires-Python: >=3.8
Provides-Extra: dev
Requires-Dist: pytest>=7.0.0; extra == "dev"
Requires-Dist: pytest-cov>=4.0.0; extra == "dev"
Requires-Dist: black>=22.0.0; extra == "dev"
Requires-Dist: flake8>=5.0.0; extra == "dev"
Requires-Dist: mypy>=1.0.0; extra == "dev"
Provides-Extra: docs
Requires-Dist: sphinx>=5.0.0; extra == "docs"
Requires-Dist: sphinx-rtd-theme>=1.0.0; extra == "docs"
Dynamic: author
Dynamic: home-page
Dynamic: platform
Dynamic: requires-python
